Metadata-Version: 1.0
Name: dada-test
Version: 0.0.9
Summary: Shared test classes and fixtures for dada-like
Home-page: http://globally.ltd
Author: gltd
Author-email: hey@gltd.email
License: UNKNOWN
Platform: UNKNOWN
